{
    "deltaT": 0.01,
    "models": {
        "collisions": {
            "compute": true,
            "e": 1
        },
        "drag": {
            "compute": true,
            "rho": 0.1225
        },
        "eForce": {
            "E": {
                "x": 0,
                "y": -1e-11,
                "z": 0
            },
            "E0": 8.854187817e-12,
            "compute": true
        },
        "gravity": {
            "G": 6.6743015e-11,
            "compute": true,
            "g": {
                "x": 0,
                "y": -9.81,
                "z": 0
            }
        },
        "mForce": {
            "B": {
                "x": 0,
                "y": 10,
                "z": 0
            },
            "M0": 1.256637061272e-06,
            "compute": true
        },
        "solvers": {
            "algorithm": 0,
            "intergrator": "1"
        }
    },
    "noOfFrames": 500,
    "objects": {
        "Unnamed": {
            "charge": -0.001,
            "colour": [
                0,
                0,
                1
            ],
            "dragCoef": 0.5,
            "dtype": 0,
            "mass": 1,
            "position": [
                -4.274386497093582,
                -0.025251431734640763,
                -9.001356948559938
            ],
            "radius": 1,
            "velocity": [
                10.596820576959066,
                -3.173457470355798,
                -0.6667765654683383
            ]
        },
        "Unnamed10": {
            "charge": -0.001,
            "colour": [
                0,
                0,
                1
            ],
            "dragCoef": 0.5,
            "dtype": 0,
            "mass": 1,
            "position": [
                0.021622751799786934,
                -4.91564368550157,
                17.535523628692093
            ],
            "radius": 1,
            "velocity": [
                2.7498809990392052,
                -6.606385625388827,
                -0.39681503547914954
            ]
        },
        "Unnamed11": {
            "charge": 0,
            "colour": [
                0.6627450980392157,
                0.6627450980392157,
                0.6627450980392157
            ],
            "dimentions": [
                82,
                74
            ],
            "dtype": 1,
            "orientation": [
                0,
                0,
                0
            ],
            "position": [
                0,
                -41,
                0
            ]
        },
        "Unnamed12": {
            "charge": 0,
            "colour": [
                0.8352941176470589,
                0.8352941176470589,
                0.8352941176470589
            ],
            "dimentions": [
                76,
                122
            ],
            "dtype": 1,
            "orientation": [
                1.5707963267948966,
                0,
                -1.5707963267948966
            ],
            "position": [
                40,
                17,
                0
            ]
        },
        "Unnamed12_copy": {
            "charge": 0,
            "colour": [
                0.8352941176470589,
                0.8352941176470589,
                0.8352941176470589
            ],
            "dimentions": [
                85,
                116
            ],
            "dtype": 1,
            "orientation": [
                0,
                0,
                1.5707963267948966
            ],
            "position": [
                0,
                16,
                -37
            ]
        },
        "Unnamed12_copy2": {
            "charge": 0,
            "colour": [
                0.8352941176470589,
                0.8352941176470589,
                0.8352941176470589
            ],
            "dimentions": [
                76,
                119
            ],
            "dtype": 1,
            "orientation": [
                1.5707963267948966,
                0,
                1.5707963267948966
            ],
            "position": [
                -40,
                16,
                -1
            ]
        },
        "Unnamed13": {
            "charge": 0.01,
            "colour": [
                1,
                0.14901960784313725,
                0
            ],
            "dimentions": [
                82,
                117
            ],
            "dtype": 1,
            "orientation": [
                0,
                0,
                1.5707963267948966
            ],
            "position": [
                0,
                14,
                36
            ]
        },
        "Unnamed14": {
            "charge": 0.001,
            "colour": [
                0,
                0,
                1
            ],
            "dragCoef": 0.5,
            "dtype": 0,
            "mass": 1,
            "position": [
                -0.020952707098885904,
                12.411405172894709,
                -7.2008768113711445
            ],
            "radius": 1,
            "velocity": [
                -2.5841967172213383,
                -3.022488984914953,
                -2.192351032530485
            ]
        },
        "Unnamed15": {
            "charge": 0.001,
            "colour": [
                0,
                0,
                1
            ],
            "dragCoef": 0.5,
            "dtype": 0,
            "mass": 1,
            "position": [
                16.56490191223934,
                0.0804641368930486,
                0.00997501095645527
            ],
            "radius": 1,
            "velocity": [
                7.714847530101749,
                10.36763762988627,
                1.4519081638705111
            ]
        },
        "Unnamed16": {
            "charge": -0.001,
            "colour": [
                0,
                0,
                1
            ],
            "dragCoef": 0.5,
            "dtype": 0,
            "mass": 1,
            "position": [
                0.018008310389460307,
                0.030881019137508833,
                16.98577509304897
            ],
            "radius": 1,
            "velocity": [
                2.3393772886877,
                3.87224507771173,
                -2.3447037225313823
            ]
        },
        "Unnamed17": {
            "charge": 0.001,
            "colour": [
                0,
                0,
                1
            ],
            "dragCoef": 0.5,
            "dtype": 0,
            "mass": 1,
            "position": [
                7.729283147561386,
                4.235601814388981,
                4.263670584924689
            ],
            "radius": 1,
            "velocity": [
                -3.4873735720137033,
                -1.1260684160882766,
                7.5780051174477245
            ]
        },
        "Unnamed18": {
            "charge": 0.001,
            "colour": [
                0,
                0,
                1
            ],
            "dragCoef": 0.5,
            "dtype": 0,
            "mass": 1,
            "position": [
                -6.402329470552159,
                0.0066462603076935306,
                7.341913233555893
            ],
            "radius": 1,
            "velocity": [
                10.296905232885694,
                0.784190715614399,
                11.612955541684261
            ]
        },
        "Unnamed19": {
            "charge": 0.001,
            "colour": [
                0,
                0,
                1
            ],
            "dragCoef": 0.5,
            "dtype": 0,
            "mass": 1,
            "position": [
                -0.07939737413372985,
                0.031206228710809202,
                -10.615247559319469
            ],
            "radius": 1,
            "velocity": [
                -10.128077598202552,
                3.9319095728830087,
                1.4260996343811665
            ]
        },
        "Unnamed2": {
            "charge": 1e-07,
            "colour": [
                0,
                0,
                1
            ],
            "dragCoef": 0.5,
            "dtype": 0,
            "mass": 1,
            "position": [
                -7.4778760494388115,
                -0.001223396818563015,
                -6.477185486803696e-06
            ],
            "radius": 1,
            "velocity": [
                -0.0005201668496634664,
                -0.15495963034712373,
                -0.0008329252110555862
            ]
        },
        "Unnamed20": {
            "charge": 0.001,
            "colour": [
                0,
                0,
                1
            ],
            "dragCoef": 0.5,
            "dtype": 0,
            "mass": 1,
            "position": [
                4.801240216811469,
                0.008693810198850524,
                25.808711866709366
            ],
            "radius": 1,
            "velocity": [
                -2.5868942939576933,
                1.1000562765414699,
                0.3002700387458464
            ]
        },
        "Unnamed21": {
            "charge": 0.001,
            "colour": [
                0,
                0,
                1
            ],
            "dragCoef": 0.5,
            "dtype": 0,
            "mass": 1,
            "position": [
                11.217255730161789,
                8.572039888211114,
                -0.0003994547120531252
            ],
            "radius": 1,
            "velocity": [
                2.7191072158933864,
                2.7523712677147976,
                0.02558383775877347
            ]
        },
        "Unnamed22": {
            "charge": -0.001,
            "colour": [
                0,
                0,
                1
            ],
            "dragCoef": 0.5,
            "dtype": 0,
            "mass": 1,
            "position": [
                -14.819883450525541,
                -0.010098345634069791,
                0.02836207141512722
            ],
            "radius": 1,
            "velocity": [
                2.6302911076061437,
                -1.2729155793947808,
                3.6641611054595806
            ]
        },
        "Unnamed23": {
            "charge": -0.001,
            "colour": [
                0,
                0,
                1
            ],
            "dragCoef": 0.5,
            "dtype": 0,
            "mass": 1,
            "position": [
                -12.884137569982286,
                4.375926671628373,
                -14.923931460512538
            ],
            "radius": 1,
            "velocity": [
                0.623233818861168,
                0.3441945312046203,
                -2.2875091132537873
            ]
        },
        "Unnamed24": {
            "charge": 0.001,
            "colour": [
                0,
                0,
                1
            ],
            "dragCoef": 0.5,
            "dtype": 0,
            "mass": 1,
            "position": [
                -9.135049918961283,
                0.07728665667278108,
                5.653880700725002
            ],
            "radius": 1,
            "velocity": [
                -15.540745121898953,
                5.364776161154285,
                -8.338755888901847
            ]
        },
        "Unnamed25": {
            "charge": 0.001,
            "colour": [
                0,
                0,
                1
            ],
            "dragCoef": 0.5,
            "dtype": 0,
            "mass": 1,
            "position": [
                -0.04593983047135315,
                0.04000633641883222,
                -0.005905547277686585
            ],
            "radius": 1,
            "velocity": [
                -5.74860180539136,
                5.089473700996496,
                -0.9096871965052343
            ]
        },
        "Unnamed25_copy": {
            "charge": 0.001,
            "colour": [
                0,
                0,
                1
            ],
            "dragCoef": 0.5,
            "dtype": 0,
            "mass": 1,
            "position": [
                1.9882080167404073,
                15.971948192876596,
                0.016269630944053166
            ],
            "radius": 1,
            "velocity": [
                -1.543888967856217,
                1.6210526102340235,
                2.0146186667517223
            ]
        },
        "Unnamed25_copy10": {
            "charge": 0.001,
            "colour": [
                0,
                0,
                1
            ],
            "dragCoef": 0.5,
            "dtype": 0,
            "mass": 1,
            "position": [
                20.01890756644868,
                -20.013582805545457,
                19.644646752156763
            ],
            "radius": 1,
            "velocity": [
                2.28207532314235,
                -1.7150313014215626,
                4.0138366766828355
            ]
        },
        "Unnamed25_copy11": {
            "charge": -0.001,
            "colour": [
                0,
                0,
                1
            ],
            "dragCoef": 0.5,
            "dtype": 0,
            "mass": 1,
            "position": [
                21.984301377343787,
                -21.982520242074237,
                -0.004187252841084764
            ],
            "radius": 1,
            "velocity": [
                -1.9733768007507424,
                2.211995726320228,
                -0.5835670700611713
            ]
        },
        "Unnamed25_copy2": {
            "charge": 0.001,
            "colour": [
                0,
                0,
                1
            ],
            "dragCoef": 0.5,
            "dtype": 0,
            "mass": 1,
            "position": [
                -13.100592983504542,
                -13.870547655949997,
                -15.318953785413324
            ],
            "radius": 1,
            "velocity": [
                -0.9655469183456641,
                0.5156209310459968,
                0.5253505961268453
            ]
        },
        "Unnamed25_copy3": {
            "charge": 0.001,
            "colour": [
                0,
                0,
                1
            ],
            "dragCoef": 0.5,
            "dtype": 0,
            "mass": 1,
            "position": [
                5.972178104738239,
                -6.046364048113916,
                0.016144154408150882
            ],
            "radius": 1,
            "velocity": [
                -3.5876124262734637,
                -5.822084131830279,
                1.9414256781680568
            ]
        },
        "Unnamed25_copy4": {
            "charge": 0.001,
            "colour": [
                0,
                0,
                1
            ],
            "dragCoef": 0.5,
            "dtype": 0,
            "mass": 1,
            "position": [
                7.9718751017966145,
                -7.9903563257823595,
                19.83346390509868
            ],
            "radius": 1,
            "velocity": [
                -3.561592250660968,
                1.2194542453014265,
                0.025590011582837552
            ]
        },
        "Unnamed25_copy5": {
            "charge": -0.001,
            "colour": [
                0,
                0,
                1
            ],
            "dragCoef": 0.5,
            "dtype": 0,
            "mass": 1,
            "position": [
                10.038213994804108,
                -10.002697461040919,
                11.478697481685982
            ],
            "radius": 1,
            "velocity": [
                4.818436200905172,
                -0.3360684769956732,
                0.8390336696100577
            ]
        },
        "Unnamed25_copy6": {
            "charge": -0.001,
            "colour": [
                0,
                0,
                1
            ],
            "dragCoef": 0.5,
            "dtype": 0,
            "mass": 1,
            "position": [
                12.033207170615581,
                -11.983989721100176,
                -0.01718718073970575
            ],
            "radius": 1,
            "velocity": [
                4.310728801784492,
                2.031642362869522,
                -2.0426054973242715
            ]
        },
        "Unnamed25_copy8": {
            "charge": 0.001,
            "colour": [
                0,
                0,
                1
            ],
            "dragCoef": 0.5,
            "dtype": 0,
            "mass": 1,
            "position": [
                16.009851189723268,
                -16.025170254516414,
                -4.83124109374734
            ],
            "radius": 1,
            "velocity": [
                1.2505852879467108,
                -3.179074486881354,
                0.023759797950170487
            ]
        },
        "Unnamed25_copy9": {
            "charge": 0.001,
            "colour": [
                0,
                0,
                1
            ],
            "dragCoef": 0.5,
            "dtype": 0,
            "mass": 1,
            "position": [
                18.005425253007157,
                -18.006738768181762,
                12.891022334534707
            ],
            "radius": 1,
            "velocity": [
                0.7409349006435104,
                -0.8527942359517577,
                -1.9945449562091342
            ]
        },
        "Unnamed25_copy_copy2": {
            "charge": 0.001,
            "colour": [
                0,
                0,
                1
            ],
            "dragCoef": 0.5,
            "dtype": 0,
            "mass": 1,
            "position": [
                5.990757312791791,
                -0.644252633177675,
                0.013898287106853717
            ],
            "radius": 1,
            "velocity": [
                -1.219645754056455,
                2.4487986394653785,
                1.7325576276379375
            ]
        },
        "Unnamed25_copy_copy3": {
            "charge": 0.001,
            "colour": [
                0,
                0,
                1
            ],
            "dragCoef": 0.5,
            "dtype": 0,
            "mass": 1,
            "position": [
                10.041358642018354,
                -2.662374799675046,
                -14.45534184226975
            ],
            "radius": 1,
            "velocity": [
                0.1905449957984518,
                0.17135121820128413,
                -1.4836580202499712
            ]
        },
        "Unnamed25_copy_copy4": {
            "charge": 0.001,
            "colour": [
                0,
                0,
                1
            ],
            "dragCoef": 0.5,
            "dtype": 0,
            "mass": 1,
            "position": [
                9.980095632216496,
                -21.39491051597589,
                19.56520751802459
            ],
            "radius": 1,
            "velocity": [
                -2.5650085797192284,
                -1.645318298100553,
                1.839216080779569
            ]
        },
        "Unnamed25_copy_copy5": {
            "charge": 0.001,
            "colour": [
                0,
                0,
                1
            ],
            "dragCoef": 0.5,
            "dtype": 0,
            "mass": 1,
            "position": [
                -6.4038665930114975,
                -6.671954197058214,
                -0.012735133232569563
            ],
            "radius": 1,
            "velocity": [
                -0.8702911472293531,
                -1.0321438328418007,
                -1.6292310274697976
            ]
        },
        "Unnamed25_copy_copy7": {
            "charge": 0.001,
            "colour": [
                0,
                0,
                1
            ],
            "dragCoef": 0.5,
            "dtype": 0,
            "mass": 1,
            "position": [
                15.961536942031604,
                -10.683612276914277,
                0.014974031352171156
            ],
            "radius": 1,
            "velocity": [
                -4.968537661393594,
                -2.5222579025521963,
                1.7509658484924424
            ]
        },
        "Unnamed25_copy_copy8": {
            "charge": -0.001,
            "colour": [
                0,
                0,
                1
            ],
            "dragCoef": 0.5,
            "dtype": 0,
            "mass": 1,
            "position": [
                17.936123686406994,
                3.2203757015185657,
                -0.009173342352409547
            ],
            "radius": 1,
            "velocity": [
                -8.091026334884612,
                -10.63309742760468,
                -1.3609192370986531
            ]
        },
        "Unnamed25_copy_copy9": {
            "charge": 0.001,
            "colour": [
                0,
                0,
                1
            ],
            "dragCoef": 0.5,
            "dtype": 0,
            "mass": 1,
            "position": [
                6.878334895800296,
                -14.671402919882132,
                0.011649774152539111
            ],
            "radius": 1,
            "velocity": [
                0.6636867346375669,
                -0.974098372486919,
                1.4875276764493548
            ]
        },
        "Unnamed3": {
            "charge": -0.001,
            "colour": [
                0,
                0,
                1
            ],
            "dragCoef": 0.5,
            "dtype": 0,
            "mass": 1,
            "position": [
                0.03547263130453377,
                5.077233727341447,
                0.008682073605471003
            ],
            "radius": 1,
            "velocity": [
                4.435105646606521,
                -6.032672244688881,
                1.21419517543168
            ]
        },
        "Unnamed4": {
            "charge": -0.001,
            "colour": [
                0,
                0,
                1
            ],
            "dragCoef": 0.5,
            "dtype": 0,
            "mass": 1,
            "position": [
                0.03895123109300281,
                5.771506694960838,
                -8.713896412085658
            ],
            "radius": 1,
            "velocity": [
                4.890163437473689,
                0.018160930085559166,
                0.5178990548700396
            ]
        },
        "Unnamed5": {
            "charge": -0.001,
            "colour": [
                0,
                0,
                1
            ],
            "dragCoef": 0.5,
            "dtype": 0,
            "mass": 1,
            "position": [
                5.716624305855693,
                0.016538833070393454,
                7.089103392965382
            ],
            "radius": 1,
            "velocity": [
                3.5261862399038613,
                2.1183980175944663,
                -9.01775364880111
            ]
        },
        "Unnamed6": {
            "charge": 0.001,
            "colour": [
                0,
                0,
                1
            ],
            "dragCoef": 0.5,
            "dtype": 0,
            "mass": 1,
            "position": [
                15.358897326305701,
                -8.435149215451686,
                13.713165447946373
            ],
            "radius": 1,
            "velocity": [
                -2.776071152997397,
                0.9399483039381087,
                -0.46595308280343295
            ]
        },
        "Unnamed7": {
            "charge": -0.001,
            "colour": [
                0,
                0,
                1
            ],
            "dragCoef": 0.5,
            "dtype": 0,
            "mass": 1,
            "position": [
                -11.329421153186992,
                -0.017779017856013962,
                -7.192698397044388
            ],
            "radius": 1,
            "velocity": [
                3.200172367391709,
                -2.2466640330426624,
                1.3125568447839973
            ]
        },
        "Unnamed8": {
            "charge": -0.001,
            "colour": [
                0,
                0,
                1
            ],
            "dragCoef": 0.5,
            "dtype": 0,
            "mass": 1,
            "position": [
                0.026460984813423533,
                -7.178737041521687,
                -0.005272425091862763
            ],
            "radius": 1,
            "velocity": [
                3.3793303261197467,
                3.264356529004098,
                -0.5736194708198692
            ]
        },
        "Unnamed9": {
            "charge": -0.001,
            "colour": [
                0,
                0,
                1
            ],
            "dragCoef": 0.5,
            "dtype": 0,
            "mass": 1,
            "position": [
                -6.962877051538548,
                6.208322524178655,
                21.308072363562655
            ],
            "radius": 1,
            "velocity": [
                0.32687211634922747,
                0.07770588778425999,
                -1.2780604205864432
            ]
        }
    },
    "stepsPerFrame": 100
}